{"type":"FeatureCollection","features":[{"type":"Feature","id":"130224","properties":{"name":"滦南县","cp":[118.681552,39.506201],"childNum":4},"geometry":{"type":"MultiPolygon","coordinates":[["@@xfTL¤cYjy\\PFIHMFMJGPKLGTPHDFBJ@RGVMLEHAT@VBL@LANGVONONWAO_cAHK@OGaCYAU@QFYLMHKBECIAG@KDmVG@ICMBGFELENSVSVQXQ\\]ITKRW^"],["@@AAC@@B@DAF@BBBB@B@D@@A@A@CAE"],["@@BDBBHDDBB@DABAACACEACAEBCB"],["@@@AACAES@DKAGBGCAB@CCC@@@@CA@CECAABCCMIOKOOIMIOWiIACC@AAABITCDJHCVC@@B@DA`IB@BADG@AAAQUEGGQKEYBcN@@@@A@GHIFSHI@A@IECCQMGMCECS@E@E@@@@@KOCAC@CAA@A@AEACAAE@CBABADE@@XEH[BMBC@@@@@GBKCMAIEOEO@@@@@E@@@@@@AAWAS@O@cBgGWAOGSEAAY_EKNMRMTIRSJSAI@@@@@@AEEEGAEBKHEJCDE@GDEDEJKLG@IBI@EC@E@ADCHGDM@MEGGAC@CB@JAP@FCFIHGFOJIJGJIJEBE@EACAAC@ODWHmNEBAJEbAJAHG@OBoCG@GBA@AhFNNh@F@DONIDIBUDUzABE@AF@XDDJ@FBJBHFJDHDBD@FBL@D@BEHELEJAN@VCDCD@B@H@DBFBFHLATLFNHLJBFBVHhBFLFBfRCLFPANAJ@FCLGR@N@VBBVBDDB|P\\JRAPClDjFP@DBJH@DBHBFFFDBn@\\CPARCRAXAV@@K@ALEJCPEL@JFLLNHPFRLTRFBF@JCAGD@BBL@@BD@@DFADB@`NFFI@A@I@@AACA@@@A@@FEHGFGDCFCFELIBCBA@AACACGG@A@CBEBABA@A@@BCBA@A@A@@DGD@@EC@@C@CL@@A@AB@@AA@@AD@@@@CA@BEBA@ABA@@BCAC"]],"encodeOffsets":[[[120981,40100]],[[121434,39950]],[[121418,39937]],[[121714,40525]]]}}],"UTF8Encoding":true}