{"type":"FeatureCollection","features":[{"type":"Feature","id":"210411","properties":{"name":"顺城区","cp":[123.917165,41.881132],"childNum":1},"geometry":{"type":"Polygon","coordinates":["@@C@C@G@MBA@@@MDCAA@EBEBG@IAEAGAMAIAIAC@CBA@A@@A@@AACB@@MBG@GAC@]EWCYEWCMAKAOCGAE@CAE@CAE@E@G@A@A@@@@@@@A@CBA@ABCBEBE@KDKBMBK@EBYPCDAF@JCHEHILEHANBNDL@@@@BHHNPRHLHPPlHPHRFBHHHLJHJHJFHBJFVJRBNB@@@@FBFBVDBBDDB@BB@@DBDABB@@F@BAB@@@@@@AD@BBB@@@BABAB@D@D@@ABAB@@BDBB@@@B@BABAB@BABABA@@D@@AB@BAB@@@B@@@DA@@BA@@BA@AB@BAD@@@HBLDHDH@H@DCBEEGGEACBCVE\\APBT@XFNFLBPAL@JF^kDQBENsFU@CAICC@C@A@E@EFG@CAC@A@CDE@@@A@A@AAA@@@@@@@A@@BABA@C@A@AAAA@CCEAKA@FAB@CAAA@C@AAAB@BE@A@E@@@@@A@@@@@@@@@@@AGCCG@CCCA@C@CBA@ABA@C@EBEQ@"],"encodeOffsets":[[126991,42882]]}}],"UTF8Encoding":true}