{"type":"FeatureCollection","features":[{"type":"Feature","id":"360101","properties":{"name":"市辖区","cp":[115.892151,28.676493],"childNum":1},"geometry":{"type":"Polygon","coordinates":["@@B@BBB@B@BB@BB@BBB@B@`JRFJ@HAH@HCHEFEFCHEHEPQFEFIHGFEHGHELCJ@N@LEHALBRAHAFCBA@@DCBA@@C@BG@E@@DA@@@ADAB@DAF@@@@BB@@@B@B@B@BAB@BABA@@B@B@BC@@@@BA@@@AB@@@@@BB@@@B@@BB@B@@@@DBBBB@D@@@BA@@B@@@BAB@B@@@@@@BDBB@@@@B@@@@D@@AF@B@@AB@@A@A@@BAB@B@B@BBB@BBB@BB@B@B@@@@@BBF@@@@BBB@@BD@@@BA@A@A@A@A@@@@AA@A@@@@B@BA@@@CAA@@@AEA@@AAA@EBEA@@CAA@CC@@@AC@@@@CACBA@@BCBA@@B@D@@AB@H@DGBAB@H@BBXADAB@FCD@FBF@DAD@DCHABAD@BBD@@BBBBBBD@L@DBBD@B@FAD@BADA@A@ABC@EBEBABAFCFCBABAHI@ABE@A@C@ABCBABABAB@BAD@B@DBBBBDBBBBB@@B@@B@@@B@DBF@H@FAFBD@F@D@DAB@D@BBDBDDFF@BB@DBB@D@DBBBBB@FAD@DADBBAF@D@BDHFBFDDFBL@H@B@BCNCLCJBHFBJCHAL@PBLBL@HLJLFHHNRbDJBFDHFFHHHBHBHDFDLR@D@D@HDFDFDJB@@DADAB@@AB@BAA@BAB@B@B@@AD@@@F@B@BB@@BD@B@BBB@@BBBCB@@BB@BBDB@@@BBDD@BDBB@@@@BBD@BB@DAD@BABA@@BC@@FBDBBBDBJ@B@B@B@DDFBDBF@BBD@@@@@BBD@D@BABBB@B@FBF@@C@A@A@AAABA@ADCBAB@@@B@B@@@B@@@BBDFBFDB@BD@@B@BBD@@@DB@BBDBBBBDBD@BB@@@BAAA@@BA@AD@B@D@@@@A@@@@A@A@@A@A@C@E@A@@PIFKBBBBDBD@B@@@BD@@@B@@@BB@@@J@@BB@@BBBBBBBDB@BB@AD@B@@@B@B@@@@@BHBB@@A@A@@@A@AAA@A@@D@BBHDDDFDJHFBDBBBB@DAD@B@DAB@B@@BBA@@F@BAD@B@@@DAB@B@@@B@@@DBDBBH@BB@fCjJIA@CCYSEE@@EECC@@@@@C@@CC@A@@ECA@@A@AAAAE@A@@BA@AHEHEBABCFGFIFGDEDC@A@ADAFGBADCDAJEFADAFAHAFAF@PAB@R@D@HAH@BAB@B@BABABCBABAFC@A@A@A@C@E@A@ADC@@@A@A@AEK@A@A@EBIBIBA@@@@B@@@D@DBBBBBDB@BBDBBBBDBB@B@DB@AFAB@B@DBFDB@B@B@DA@@@@B@DDBBBFBHBHBD@D@J@B@B@DCJ@BAD@F@JAF@BCFCJAF@BCFAFADAHAHAB@D@D@F@DBDBJBBFNBBBBBBBBDBDDHBHDD@D@D@B@@@FAn]DCj_FCf]\\SlFH@DB@E@@BCB@@@@AB@@@@A@@@@BA@@@@@A@@@@BC@@@A@@BA@@@@@A@@@AB@@@@A@@@@@A@@@ABA@AB@@@@A@@@A@A@@@@@A@@@AAA@@@@@@@A@@A@@A@@@@@AAA@@@AA@@AA@@A@@@AA@@@@A@@@@AA@@@@@A@@@@@A@@@A@@@@BGHI@EBA@AAAAC@A@ABC@@@ABGAC@E@CAE@GBC@AAI@G@EAAAIACCAGCMEEAC@GCCA@AIGAAAAEGACEGAEAACICEAA@CACAGBIA@A@A@A@AAA@AA@@@@@ACACC@A@@@AAAAC@@AA@@B@AA@@@@@@@@AA@@@A@A@@B@@A@@BA@@@@@A@A@A@AAACAAAA@@BA@A@CBA@CAA@CAA@A@@@ECCC@AYCSCIAG@SAI@GBGDMBGBIAICICEEEEAEAE@GHGFEBE@GBGACEGEE@GDGBIBGBEDEDELAB@@BFAJ@HBF@HBLGBC@CDABAFED@D@HBD@DADADABABCDGDCFCJEBABABCBABC@ABCBE@CBC@C@C@A@CAIIK@@DBFDHDFDHDFDFDHBD@HDHBD@DAB@@G@E@CB@@ABAB@BABADB@@BB@@@BB@@@D@@BB@B@@@BBBB@BAB@B@BA@@BA@H@H@D@BA@A@AACBEDGHGBCBCBCFCJCH@JCN@LEH@HCFCLGFEDCLKBA@EBEAE@CCCAC@@AC@CBA@@@@@ABA@AA@@AAAAEACAA@ABA@A@AB@@@BADB@@B@B@@ABA@A@C@C@EBA@CBAAAAEAACEACAA@A@C@E@ABADCBCDCFCDABA@@DEBABCDABABC@ABMDMJQHQJOLKHOJIHIHEPIHGJGJKLGHGHGFKJGFEHEBCDCBEAICGAG@EBCDEFGDG@IBIAG@CAC@EBA@@CABAB@B@BAB@B@B@B@@@AABCBAAA@ABAAAAACAA@BCB@BA@A@A@A@AAG@AC@A@AA@ABCBAAAC@@ABE@AAAA@ACFABA@@AAAAAAAAABC@CAECCCC@AAMICACCACAACAIKECEE@CEGEGAECGCECECEAC@I@EBGBIBI@IAEAEAECECGCEGCEAEAEEGEAEAGAGG]CKCG@ECEGEGCQ@CBGBKAK@K@I@K@GAGAGAEAK@ICKCIEGI@I@MEIEIGGEAC@EBCNBJAHAHAFEFGBGDGDGFEFEDGBG@ICECCCAKBK@EACCIE@EBEBCDCBCBOEOCKCGCKGKCGEIEIEIEGGCCAG@M@G@IACCE@@@A@C@C@A@CACAA@@EBAB@B@BADABCBEBIREFIDG@OAUBKFQLGHAFBFBH@LGRILKFOFKBK@OHIDCBBBABADAB@DABABCBCBC@C@ABA@ABABAB@B@BA@@H@F@B@FADAD@@@@CFABCBA@CBCBA@CBABA@@B@@CFEJEFCFE@K@ODODEBA@C@EAEEIGCAAACAA@AAC@AAIAC@@BAACBC@A@AC@A@AAAA@A@C@CBCBA@ABAB@D@BAB@BGDGDC@CBCAA@AC@A@A@EACAAAAAAAAC@CACACAGBA@GDC@A@A@C@ABAB@BBBBBBB@BBBBDD@B@BBBB@BBB@BADABAB@B@B@BA@A@A@A@CBAB@BABE@A@EBCD@@A@ABA@CAAAA@@B@DA@CB@D@D@@ABC@ABA@C@A@AAAAAAACAAAA@ABADAAAA@AAACCBA@CB@BABAB@B@B@D@B@BAB@BABA@@BCAA@@CAA@A@A@AAAAACAAACAACAAAAACACAAACAAACAACAACCAC@@@@BCLKTKLKHAB@B@D@B@D@DBB@DBDBB@BBD@DBD@D@B@DAD@D@DAD@BADABADAB@BADAD@BAD@H@@GTADCHKJKLMHKHABA@CBGBC@CACAEAC@C@EA@E@EBEBI@CAECAC@EACACACCACCAAA@AAAA@EEAA@AACCAC@A@E@CBCB@@CDEBCBABABMEIEMIEEEEEAAAC@CFADEJADC@EBCBCDCBCBA@AAAAAAC@@@A@@BGBABA@C@A@@AAAAAA@A@@AAA@@AB@@ABA@@BB@D@@@@B@BABAA@BA@@@A@@B@@@@@DAB@BABC@A@@@A@CBA@@C@ABCACAA@AA@@@A@@@A@AB@@AA@C@C@ABC@A@ABA@A@@BA@BB@BBBFBDBB@@BB@@@@BB@@@@B@DB@@B@BE@@@@F@B@D@DAB@@AAACC@@B@B@B@B@BA@C@@@A@AA@AA@@AEA@A@A@A@A@A@@AC@@A@@@AAAA@@@@@AAAC@@BAB@@@@@@AB@BA@@@@A@C@AAAB@@A@@B@@AB@@A@@AAACCABABA@DF@B@B@@@BAB@@C@A@A@E@EACA@A@@@AAAAC@AA@CA@ACA@AA@@@A@A@@@A@A@A@AB@@A@@@CB@@C@A@GBC@@AA@A@A@@BA@@@@@@@@B@@@@@@A@@@BB@@@@@@BB@@A@@@@@@@@@@@AB@@@@@@@@A@@@@B@@A@@@@@@@ABAA@@A@@B@BA@@@@@@B@@@@@@@@A@@@@@DBD@FBDB@@BD@BBF@DDDDJBBBDHFFDFDD@DFDDBD@DAB@DCBADAB@BADADEDCBCBC@K@E@@@E@C@EBCDABCF@BAD@F@BBBDF@DCDC@CAAAEBK@E@A@A@@@A@@A@@@@@A@@@@A@@@@@@@@@A@@A@@@@A@@@@AA@@@@@@@@AA@@@@@@@@@CC@@@@@@AA@A@@A@@@@A@@@@@@@A@@@@@@@@@@@A@@@@@@@@@@A@@A@@@@@@@@@A@@@@@@@@@@@@@@@A@@B@@A@@@@@@@@AEEAC@CAE@C@E@CBCBCBCAAA@AACCCACCCCCC@E@CBCBEBCBED@@@@@@@@A@@@@@@@@@@@@A@@@@@@@@@@@@A@@@@@@@@@@@@@@@@@@@A@@@@@A@@@@AA@@@@@@@@@@A@@@@A@@@@@@B@@@@@@A@@@A@@B@@@@@@A@@@@@@B@@@@@@@@@@@B@@B@@@A@@@@@@@@@@@@@@@BB@@@B@@@B@@@B@@@B@@@@@@@BB@@@@@@B@@@@B@@@@@@@@B@@@@@@@@@B@@@@@BBBDDBBD@D@D@D@D@BBDB@DBBBD@BBB@F@D@D@JAD@@ADADADADCBABEDA@ABBDDBDDBBBBBBBDBB@@@B@@@@@@@@@@@@@B@@A@@@@B@@A@@B@@@@@@@@@@@B@@@@@B@@@@@B@@@@@@@BB@@@@@@@@@A@@B@@@@@@@@@@@@@@@B@@@@@@@@@@@BA@@@@@@@B@@@@@@@@B@@@@@@@@@@@B@@@@@@@@@B@@@@@@AB@@@@@@@B@@@@@@AB@@@@@@@B@@@@@B@@@@@B@@@@A@@B@@@@@@@BA@@@@B@@@B@@@B@@@B@B@@@B@@@@@@@@@@@@BB@@@@@@B@@@@@BB@@@@B@@@@@@B@@@@B@@@@@@@@BB@@@@@@@BB@@@@@@@@@@BB@@@@@@@@@@@B@@@@B@@@@@@@AB@@@@@@B@@@@@@@@@B@@B@@B@@@B@@@@@@BB@@@@@@@@@B@@B@@B@@@B@@@BB@@@@@@B@@BB@@@B@@@BB@@@@@@B@@@@B@@@@B@@@@@@@@@@@@B@@@@@BCDA@CBCBAD@B@DAB@D@DBBBDBBDAD@DABBDBDABDAD@BAD@BAD@DABAD@D@DA@BB@D@DBB@D@DAD@DAB@DAB@DADABADAD@D@B@DDBBBD@D@FBB@D@D@FBD@BBDBBDBD@BCBCBAB@D@B@B@D@BCDGDCBCBAAACCAAACAC@A@A@@B@BA@@AA@@@A@ECBCCAA@A@sD@@@@BB@B@B@@ABBD@@@B@@ADCB@@GJA@@@B@BA@@@AB@@BB@@B@@@B@B@B@@@@@D@@D@B@@@@@ABA@AB@@@@@B@BBB@B@@C@@@@BB@B@B@B@@@B@@B@BBBBBD@@@B@BA@AB@BBB@@@BB@DB@B@@@BB@@BB@BB@BBBB@@BB@@BB@@A@@BA@AD@@@@ABCD@@@@B@@@BBAB@@@@@BB@@@@@CB@@B@B@@@B@@@B@DBADABABEDABAD@DFFBD@BBH@L@F@B@@BD@B@DBD@B@DBB@DBBBBBBBDBBBB@DBB@D@B@B@D@B@D@BADABCBAB@B@DAB@DA@AB@D@BBDBB@BBDBBBBDBBB@BBD@BBBBD@BD@BBABABC@ABC@ABABC@CBC@AAC@C@C@A@C@ABCBABABCBABABC@A@EAEG@ACAAAEAMB@@CBKDE@E@E@@AA@AAAAAA@ACAA@ABABC@ABAAAAAA@A@A@AACA@AAA@CAA@ABCBABCFAJC@EAC@EDCBC@DF@D@DEHCH@FCFABCD@DJ@B@@DEHABAD@DDDBBDADAFBBBD@BAACAAACBCD@DFDFDDDF@DBFDDABE@CBBDD@F@D@BDABAFFDLBF@JBBB@BBDBHADCHBFBDBB@DDDB@DDAFAD@DBDBFDFBFBF@BBA@@B@BA@@FEFE@AB@BABCB@BBBBDFDBB@D@DBBBBB@B@D@B@DBB@DBBBBDBBBBBBBBDDBBD@B@BADAB@BADABAB@D@BAD@BABAD@BABADBBBB@D@B@B@D@BABABCBABE@A@A@AB@@BD@B@BABAFCDADADABAB@@@@@@@@AB@@@@@@@@@@@B@BA@@@@@@B@@BD@BBDB@@BAB@BCDABCBABAD@D@DCDCDCBAB@D@@AF@@CFGFAFCDCJ@BADGB@BC@A@AF@DCDCHCDAFADBDDB@@@@@B@@B@@@@@BB@@@@@B@@A@@BB@@@@@@@@@@BB@A@@B@@B@@@@A@@@@B@@@@@B@@@@@@@@A@@@@@@B@@@@@@@@@@B@B@@@B@@@@B@B@D@AD@BAB@@AB@B@@@B@B@B@BB@@B@BB@@B"],"encodeOffsets":[[118247,29703]]}}],"UTF8Encoding":true}