{"type":"FeatureCollection","features":[{"type":"Feature","id":"360601","properties":{"name":"市辖区","cp":[117.033838,28.238638],"childNum":1},"geometry":{"type":"Polygon","coordinates":["@@GFAFAHCB@@ABA@@@@@A@A@@@@@AB@BAB@@AB@@@@@B@@AB@BB@@BA@@@@@A@@BA@@@GBAACACBCBCDADADEFAF@@GDMPMFOBKAMGASQDMDOLGLOJOEMIO@WPELKFOCMSCO@MEGILIJGDMAIIIGKMGMKMMOKKSBQLGJENILEPATDPFLXbHLZRFR@RARAJIHKLSLIJgRABOT@BEDEHEBEDAHEL@FAB@BA@@B@BABA@@BBB@BA@@BBB@@@DBB@B@@@@@B@DI@@@AD@@@B@@E@ABICA@@AA@A@A@@@ABAFC@@@A@@A@A@@@@@AAA@@DA@@AA@@@@A@CBA@AACAC@EAAB@B@@BBBBBB@@BBDF@B@DBB@BAB@B@B@D@@A@@@@F@@BDDBBB@@@BC@CB@@A@AA@@@AC@@BA@@@@DADCJ@D@@AF@BB@@D@BAB@@BD@DCDEDCBA@ABCBE@ACCEAGACCGAGAECCCCE@G@I@EBEBGFEDCFGHEFGAKDIBEFIFEDGHEFGDG@G@EBAAGCEAECIAE@GBEFAFDBDDAFCBCBCDEHCF@FBJ@D@H@FBFDJDFDFHHBHBF@HAFEFGDGBGBI@K@KESAICEAEBEFEBGDG@E@EBG@EDEH@DBLDFDH@DCDE@KCEDI@G@GBEDIFIJ@J@D@F@LFJHJLJDFLFLHPHJDHBHBH@J@HAFAJCDCFCFAH@F@F@H@HAFAFAFAH@J@FBDF@FBDBBBDBFBJDFBHDHBL@HCHEJGJIFEJAHAJCHAHEJINDDDHBHDHFFLJNJNLNJHBF@JANBP@H@F@JBJDH@HFFDBD@F@D@DAHEDIPABCFBJBDBJBFFFHHDFHHDFFHJNDFBFADAFCFCJGJEHCHCFAFAH@F@H@DDDFAHAJCJAHBHBBFBDBFBNFFFDFAH@FBJ@J@NBRDHAD@J@JDBDBFHDD@F@FEDGHG@@BCBEBCBCBA@A@@AA@CB@F@B@@@BAB@@A@A@@AA@ABA@@@@BBB@@@D@@CBA@A@A@@@A@@BA@@DCB@@@@@@B@B@BBB@BF@BBBDBB@F@@@BD@@B@@@BCBAB@BB@DBDBBBBDBBJFB@DBFBBBD@BBB@@B@H@@B@HHFHFFFHDFDHBFBFBF@HCJENEJAJ@JBFDFFFHDJFLDFBH@FAHAHEDEDEFEFEFEHCHEJELENAJAFAHCFEJCFEHGLDFDHFFDJFJDHDLFLHTJJBJDBBB@@@D@HDBBFFBBBF@D@B@BBDB@B@@B@BBH@JCDAD@BBBD@JDD@HA@@AA@AC@AAAA@A@@@@B@DBFBDB@@DADEFGBAB@HAH@H@FCFCFCHEDG@GBEBEBCBIBEDEDEFGFGFGDEFGBGDEDGDGFCFCFCFEBI@EAEAI@I@GAG@IDG@CBGBE@IBMDI@G@KBGHGDGBG@E@EAC@EAG@CIKCECCCCCEACAEAGAG@GDEFCFEDCHAHEBEACAECCCEACAEAECS@E@EICGA]MGEQSAEBOGIOAODA@A@CAAA@A@CDEDK@@HO@AAECGB@HA@@CC@ADAB@@@FBB@D@D@DAB@B@B@B@BB@@BABAB@B@DA@AAACA@ADAB@BAB@@A@ABA@ADA@A@ACA@@BE@ABCBA@A@AB@@@FABABA@ABA@ABABA@AAA@E@@EAAAAAAEBE@ACAAAA@EAA@C@AAAA@AGICEECEI@CBGDIDIFGDE@GAICIGGECCCAE@EBGDIHCHCHAN@NCLAH@HCFCFCHEHCJCH@HBFBFBH@H@L@HATKLCLGRENCLAJ@JAHAF@HAJADAHEDGDEHQHKHIDGFEBGFE@M@MDMDMBI@K@EAE@A@A@C@AAECECEOYCECMCQ@GASKOGM@@CECGBGDEVC@AB@ACAAAC@AACCACAEACAAAAA@CAC@AAACCCCGEIGCCCEAACCEAEAG@E@C@A@CCECAAAAA@@@A@AAA@@@A@ABABA@C@@@A@@@GCCAAAC@CCCCACEICECCCCAC@A@@@A@C@AAAAA@@A@AAA@@@CAC@A@C@C@@B@@ADABCBCBA@@D@DBBBD@DAB@BBD@DBDAJAJCDCDEDCBE@A@C@@@CAACEGAAACCAAA@KKIGCG@E@A@AACAA@@A@@@@ABA@@@A@@@@B@@@BA@@@A@@@A@@BA@@@AA@@A@BCBABA@AACAACQAK"],"encodeOffsets":[[120092,28517]]}}],"UTF8Encoding":true}