{"type":"FeatureCollection","features":[{"type":"Feature","id":"411701","properties":{"name":"市辖区","cp":[114.024736,32.980169],"childNum":1},"geometry":{"type":"Polygon","coordinates":["@@@@GBIBGBGACAKIKGEAEEGAEICEACCAC@CBEF@D@DBFDH@D@F@DABEBWJC@GCC@C@EDKJEFABEF@D@D@DABBJADCDCBGB]GUGC@EBCDGJGFIFKDSHI@ODIDeJODe@S@C@IEcOGAK@GBEDEDEBAAE@KG@A@CBC@CBC@CAGIKAEACACAC@AAAEAG@E@KDGDADCBG@EBCAA@AEAAA@C@C@EDE@KBQASBE@AACACE@IACA@CAG@A@EBEBCDE@A@CACCCG@IBOBMBEBAD@D@DBF@BALODM@G@E@CAAIGECAAC@E@CAIEEECCACAGAC@ABCDCBC@@BEBCDAF@DABCBC@CAECCACA@AAEAK@MBSNEB@DADADADA@I@CAKEGCEAC@E@CBABERCV@@@@AFAFA@CBE@GCMECCCCAC@@@@@@@ADIBG@EACACAACAMAEAEBE@C@E@E@A@CDCFCHCDABCBC@IBOAEAEACAAAGECCEAUKKCAAA@C@@@EBADA@ABA@A@I@QBI@C@A@GEICEA@AAC@K@I@AHCBE@CEMAGAE@E@ADEB@LEFCFCBE@AAI@CCC@AAAC@CAA@CAAAAAACACAA@C@@BABA@@BEBABCDAXCLATGjWTMJILIDABC@AAA@C@A@GAAACGAKCKAE@EACCAC@EBIDE@C@AAAG@OCCAAC@E@I@CKQC@EACAAEACCACAS@EAAA@CDCJKMBOCGACACKACACOMKECAC@GBC@CFKPCBEBWDWBG@EAAC@C@M@EACCAC@CDOLEFA@C@C@IGUQEAC@C@CDKLCBCBC@EAEEGKACA@C@ABIJOLEDIBIA_@EBCDAD@@AB@DABBBBD@BAFAJCDMFA@CBCBADCBE@AD@DBFAD@J@VCRCNADA@EDEBK@ODIFEBEACECAC@G@GEIAC@ABABEFAD@FDFAFAL@DAF@DAB@@A@ABAB@@@B@D@B@@@F@@AB@B@@BFFHHJBB@BABCBACM@@@@A@A@A@CCA@@C@AACAAAA@A@@@A@A@C@A@A@@B@BBB@B@D@@ABABABAB@B@B@BA@GDABABAD@B@@BB@BB@AB@@A@AAA@A@AB@B@D@DB@BDBB@B@BAB@FA@AD@@@@B@BB@B@@@BABABAFABADA@C@CAECEAG@E@CAACACAEAAEAGAG@E@EBEFAF@DBBDBJDDD@BBFCD@HA@ECC@CACBAB@B@PAH@NADADCBCBC@I@GAUGEAAA@A@G@EACCC@E@A@EBE@E@ACAAAE@A@IBI@CBGBEBA@A@WOECMGEAG@E@C@EDGDC@C@A@EAC@C@EBADAB@D@HARAP@FB@B@B@F@D@BB@D@DADEFEBEDABGPAJAD@BBDBD@D@DAD@DCDCDAD@D@F@F@DABABCB@DC@IEACAE@O@EAAEAC@E@E@CBA@A@CCCACAI@QAE@AAEGEECCGBEB@@CC@AMCKAG@EBC@C@C@CAC@G@EDMNAD@F@J@FADABCBCBAB@B@H@HCFAFGLCDAD@B@BBBDTBH@DADA@CBGBABIJEHENCNAHABABABE@C@WCMAC@CBEBQTILABEBA@EACACCAACAIAC@A@CDCDCBA@CAEAC@C@IDE@CAEAACAA@CBIAQ@AAAC@EBIFAFCFGHCDAJABGDGBCBCDAD@DBFJPBBABABC@C@CBCHCFCBGBE@ABAAAACACAA@C@AB[RMF@@A@UJIJINCFCBMFKFGDEFCBGAGAICAAC@CBEBCAAACBCDCDEBGDCBCFCDADCBKKA@A@EDABC@C@GAC@CBCBCBAD@DABABA@A@CCEKCI@E@ABCBAFADABA@AAE@EBKBKBE@CAAA@EAM@E@UIA@@ABAFEBABA@AACCAA@A@A@CBA@A@@@AA@ABGAGAACGCEKIEACAACAC@CAMEOA@@EA@@AGEEAOIKECAA@A@A@GBIDEDC@A@AACEGIACGG@A@G@C@ACACAOCEAG@CBCBEDEDKHEBGBC@A@CAICCAA@AB@D@PABA@A@IAEAC@EDIFEFGJCDC@CBADCFCDCBKBEDEDEBEAEAACCCEGIIIKAA@EA@CCMUEGCCAA@@A@C@CDEBEBE@EACAEEAAA@A@ADADABC@GDGDCBCDCJAFABCBAAC@CECCCGAAA@ABGNCBOFODA@C@CHA@EAGACAKDE@A@CAKBC@A@ACAGCGEMECGEKCMAE@SAG@C@ABABBD@B@BABEDCB@B@DBBBD@PAHADEF@B@B@DDFFDBD@D@XBL@BABA@G@E@CBADAFEHADBFBFBDDBJBDBHHHN@FBHDDDFFDNFDBHAFAHCDABABCBEDCHEJCF@B@@ADGHQB@B@B@D@DFFFBD@@CLELCFCDMFOBE@CAEBC@@DBBFDBD@FCHCFEDEBC@E@M@GBC@GHCF@D@B@F@DABCBEBC@GCCAC@@@ADBFBF@D@F@DBBBBHDDDBB@F@HCJADGJOPSTAD@B@BBBLLDF@B@BAD@DBFBB@BABABCBEDA@@B@B@BB@DJFDDHBD@B@BA@CBCBCB@BAFGHMDABCFBFBHBDBBDDB@DBDBB@DFLR@@@@@BDDDBJFB@BB@@@BA@AB@B@BBBD@D@@BDBJNIH@B@@@DBDDH@D@HDLFNGDEBEBE@CAWBOHIBIBEBEHCFADCDGDCBA@AAAE@GAACACAEBkDEBABADABBDAD@@C@C@C@EDCBAD@@BFDFFHBJBHFPFJHRFNDPDFJLRJH@DDDDBFHLNLLJ@DBD@FBDDDFBNBHBDBFDDDBDBF@@@@BD@DBBFDFDD@H@F@@@@@D@LEFADCB@B@B@BBHDRNFDBBF@DAD@D@D@DBNLD@F@F@BAJCF@B@^@X@DAHCFAFAD@HBHDFBPNJBNDPDH@FDFDLLHFDBHBLFDJDLBJ@HHTBLDFDFDBRHJDJBJ@H@JAHBJDJBH@FAFAFADAFALBNALAFBFBF@H@DAD@B@DBDDNHDBDAB@BCJKDAB@F@F@BAD@BAFGJIJEDAB@BBFHDHDDBF@F@HBBBBB@HCLCFAJ@P@JBD@DBDB@BBDBB@@B@DCHGLMHEBAD@DBFBFDDDNPFL@@@@DHJNHJ@D@BCBCBEAC@C@EBC@A@ECABA@ADEPCFAFCFCFEHCPCTADADAJ@D@FJ\\BLFZFbHRDHBJBDBBPNFDDF@B@F@N@LBDBB@F@FADCD@B@BBBDDDBBBBHDDHFDDBBH@LDFBH@FDDBBBDHBFBB@B@B@@BBBDBDDNDPBBBJBFBBBBF@VCD@D@BDDXBDF@HBAH@F@B@BDBBBBHAj@H@DBDBFRFHLBPNFFJ@LBLFJFFFJNBBHBL@J@`AZBH@L@LAFA@A@ABAF@FCHELEJAJ@B@FFJHDDD@F@PFB@@F@BBBDBNAF@DBBBBFBDDDHBDFBL@@D@D@BD@DAFBDBBB@B@D@LCDBBDBHBN@@FBJ@JAFBFBFFDFDBD@H@HADADEDCDCFAJ@FANCVMFADABBB@D@B@@ABA@ABCBCPDABVHBCDC@C@@@ACAE@CAC@MC@ABC@@@A@@@A@AAAA@@AB@DCB@@ABBBAN@@BB@JFFBBBB@HBBA@@AG@@@ABADC@C@@@A@AA@C@A@@CBC@AA@@EBA@@@ABA@@F@@@FBFAB@D@B@BAFABA@@B@DA@ACEAA@ABA@ADAD@DAFA@AB@FBJBHBHAFCDEBCACAAEAICAC@CBAFCFERMJEBCDJAHBHBPBFBBFBHBLFD@F@NCHALBHDPFJFHBX@HBJFZPNFPFDB@B@BB@BBB@D@DANENEJCBAFCDCJCF@NGBCBA@C@E@CBADAB@D@B@LFDBB@BABADI@ABAB@D@BBBBDFDDBBFBD@J@H@LDF@BBBBBBBBD@DBF@L@JBZDHBJ@DAB@BABEBADAJEDABA@A@E@K@GDCDAB@DBB@HHFBJ@LCHE@ABCAKAM@G@A@@D@T@ZBTBF@FDHDFFD@@@B@FCF@F@D@BDBBB@D@DADADAFA@@BIHIDCBCDEAK@E@CBCFEDA@CAECEAC@A@ABABAD@F@FAB@BAB@@C@C@E@CBADCDAHAHAF@DABAFGBCFEDEDCDAFAFAD@D@LBHBHDFBD@D@DADAFCFIBC@ABK@CBCDCDAHABA@@@AACCEAA@ABABAD@B@B@BBB@@BBDB@DBF@F@B@BA@C@AAAAA@AAE@EBCBABADAD@FBHBHBHBDBN@N@FAAC@ABEJEDEBG@EAGAA@EFO@KAIAKC@EKACBIACEIAAAE@E@AAAGCGCGEKKAA@KAKCAKWGGISJ@FADCB@FIDAFAH@B@BA@E@G@C@A@CB@DAJ@B@DABA@ABCAC@C@CB@BABA@@BCAC@C@CBABAJCJC@ABCBG@@BAB@FBB@B@BABC@GBAF@J@NBDADA@ADOBGBADADA@ABA@QAI@CBABADAFAF@RBF@F@B@BCDCBC@CBEBAB@BAFBNDJBFBNALAFALGFAF@D@D@B@BBBBDPBH@LAFB@@@L@PDF@ZBNBDBB@BFAFNBD@BADCDAF@@ADEBA@CBA@CB@@ABA@EAA@@@AAAACACAA@ADEBABCDC@ADE@I@C@C@@@A@@@CBAB@B@@ABA@@BAD@@@BC@@DAB@B@@@FE@A@@A@A@AAA@A@@@AAA@@@@@@@AA@@@@@@@A@@@CA@@@@@A@A@@@@@@AA@@A@@@A@@@@@@A@QAC@A@QDWF@AAA@CFILKBGBA@ASIICCACA@AAEBGFIHIHAJCL@N@F@D@BCFKDEDCFAHADCFCHSDIDEDAF@F@JFHFD@H@NBL@NBXAXALE^KFABABEDCBABC@C@AAAAAOC@@A@AAAAAA@A@ABABAFATAN@F@HALAPAPBP@D@DADAHEFEFAFAB@FBBBHDHDD@F@H@JARAF@B@DCBABA@AACAE@A@C@ADADCJAB@DCBABEAG@GBCHENETEH@JBLBHADADCDGBGBE@ACAKBIAAAAEBEBALI@@@CACEGCK@C@EBAHIDCHCLEDEHI@A@AACC@E@I@GBGDEDA@C@EACAAA@CAGBEBCFABCDABC@E@ECECMGYCAAA@A@GAGBE@EBADABABA@C@EAICEAEAC@E@ABEDCBAAE@ECCACA@@A@A@@DAD@B@B@@CBCAA@I@EAC@A@@BAB@@@B@@BB@B@BB@@F@B@BBDB@BBB@B@@ADABEDCDCD@BBBBBDAD@HEHEDCDC@E@E@A@C@@@A@C@C@ACE@A@AB@D@B@DBB@BB@B@D@BB@B@B@D@B@D@@@@A@@@AAEAAAAAAA@AAC@CAA@@@@A@C@C@ABA@A@AB@B@F@@@BA@@AAEAAAAAA@@@CBCBAB@@AB@BBD@B@B@@ABC@A@CAA@AAAC@A@A@C@C@E@A@A@AB@B@BBBBBB@@B@BABA@GBCAAACAAAC@A@@B@BADAHEDA@A@AAAA@CAA@@CA@@AAB@BC@A@C@AACAAA@@@@A@@@@@A@@A@A"],"encodeOffsets":[[117957,33386]]}}],"UTF8Encoding":true}