{"type":"FeatureCollection","features":[{"type":"Feature","id":"520112","properties":{"name":"乌当区","cp":[106.762123,26.630928],"childNum":5},"geometry":{"type":"MultiPolygon","coordinates":[["@@@@@AA@A@CBA@ABA@@BBDD@@@BBB@@CB@@@@@@BB@@@@@@@B@@@@@B@B@A@B@@@@B@ABB@A@@@A@@@@@AA@BAA@A@@@A@AA@@@@"],["@@A@@B@B@B@BB@@@BA@A@@AA@A"],["@@@@@D@@B@B@@A@@@A@@@@@@A@@@@@A@"],["@@D@@A@@B@@A@AA@CA@@@@@@A@@@@AC@@@@@@@@A@@@@@@A@@@@A@@A@@B@@BB@@A@@@@B@@B@@B@@@@@@@@A@@@@B@@B@@@BA@CB@@BBB@@@B@B@@@@@@@BB@"],["@@@@A@@@@A@@@A@@@@ABA@A@A@@@@@@@A@A@@@@BA@@@C@@B@@@@@B@B@@A@@@@@@A@@A@@AAA@@@@@@@BA@@B@@A@@@CAA@A@@@A@@@@AAAA@@AA@@@@AA@A@A@AAA@A@@A@@@@AA@@@@AAA@@AA@AA@@AA@@A@@@@AAA@@@@AA@@CA@AA@AAA@AAEA@@A@A@CAC@C@@@AA@@A@@@AA@@BAB@@A@@@BB@@@B@@A@@@@@ABBB@@@B@@@@A@A@@A@@@A@@@B@@@AA@@@@@@@BA@@@@@A@A@@@BA@@@A@@@@@@@@A@@A@@@@B@@@@A@@@@A@@@@@B@@@B@@@@AB@@@@@B@@@@@B@@A@@@A@@D@@@@A@@@A@@@A@@B@@@BCB@BA@@@@@AA@@A@@@@@A@@@@@@A@@B@@CBA@A@A@@@@@@@@@@B@@@@@A@@A@A@@AA@AA@@@@A@@@A@@@@@@BA@AAA@@@B@@AA@@A@A@@B@@A@A@BB@@@@@@B@@BA@@@@@AA@@@@@A@@@@@@A@@@@@@A@@@@AA@@BAAA@@@@@@@B@BAB@B@@AB@@@@@@@A@BA@@@AD@@@@@AA@@A@@@@AA@@@@@C@@@@@@@@@@AA@A@@@@A@BA@@A@@@@@A@@A@@@@@A@@@B@@@A@@BAA@BAA@BC@@@@A@B@@@@A@@B@@@@B@@AB@@@AB@@C@@@@@@@@@A@@BA@@@@@BBFFABABA@G@MBUDOBEBDFF@JFFBBB@BEHAB@B@D@DB@DBD@FHAFEBGDCDCDA@CAACACAEAAIBE@G@CBC@ABAD@D@BBBDB@@A@ED@B@BDBA@ABA@A@@BABABABA@A@@A@AA@C@C@CBABAD@BBBBDDB@BBBA@A@C@ABCBA@A@ABCDAD@B@DAN@@@BBBB@BAB@BB@DAD@D@FABCCC@A@BDDHBD@@B@B@B@BBBB@D@@@DAF@@FDDBDD@BD@F@DA@@DABADABAD@FBD@BABAB@@B@D@BADAD@B@BCB@BBDBFB@ADABBBBDCBAB@D@DBDFHC@C@A@C@ADABC@C@BD@DBBDAB@ADCBADA@@DAD@BCB@BFBFH@@B@DBFFFBBBF@B@@ALBFBBBDDDBD@T@B@DBBBBB@D@DFJBB@BBF@JBFBFBDDDDD@FDHDBD@J@DBFBAB@B@@@BD@B@B@@BD@@BABABBF@B@BCBADA@C@C@IEA@ADC@GAAD@BABA@CB@@ADCDADEFCBGHA@@@A@C@GCC@C@A@@B@DA@AAA@EBDDDB@@@BBDB@@@BB@@ABAB@BBB@BADHCBBBD@BGDCBABA@@BCBGBCBAD@D@BBBF@F@DBBBBD@D@BADCBCBC@ABC@C@EAA@AAAACAA@ABAB@B@B@BBBFDDBDBBBD@F@DABADA@@B@D@DB@D@D@B@D@BDBHBB@BBF@F@F@DB@@DDBDF@DAB@DAFADAB@D@BBBB@B@BDBHJ@@D@FCD@B@@B@@BBB@B@D@B@B@D@F@DDDHFDFDF@F@B@@A@ABAD@DH@@@BBBBABBBB@BAB@BDBB@D@BBFAB@@E@CAEAC@CBABC@A@C@C@AHCFALAD@D@B@BB@BBBD@FBB@@BABAB@B@DB@NDRCNAJBNDJHTJLBJBJCLIHOFOFIDEDCN@NDHBHHLNFDFDFAFG@ICW@MDMHMDOAKCKEGGGKIAEDEFCVOVMRGBBB@@B@DB@B@BABABCBABA@C@CBA@A@ABAA@@AA@@E@A@AA@AAA@A@A@@BA@A@@@@AACAAA@A@C@E@A@G@CAA@CCGEEG@AA@@@AA@@AC@@AAA@ABA@@@CBA@ABA@A@@@CAA@@AAAA@ECECAAA@ABABED@@C@C@@@C@AAAAEEGE@@ACAACACC@AAA@AAI@ADAD@BAB@B@FBBBB@BADCBCA@@A@AABA@AA@C@@C@C@A@AABC@AAAA@ABCBCDABAABE@EBCBGDEBB@@BA@ABB@@@B@BB@@@DM@K@EEEGAKAKAIECIAK@IBC@C@CAC@@@C@A@A@ADBB@FDBAB@B@ABBBD@D@B@@ACAAEA@EAIAD@D@F@D@BA@ABABEAAC@AAABA@ABCBAB@@A@@@@@AA@AC@A@@BA@AAA@A@E@@@C@@@@@@AAAC@C@AAA@AACAAAA@AA@@@@AA@@A@AAAACAA@A@@@A@AB@B@BABA@@B@@AB@@@@@BA@E@E@@@A@A@AACAC@AAA@AAAA@@@C@@AA@A@CA@@@A@@BA@A@@@A@A@@@A@AAA@@@ABA@AAA@@A@A@A@@@@@@CAE@@AA@@BA@@@@@@@CA@@@@@A@@ABA@@@@@@A@A@@A@@@ACB@"]],"encodeOffsets":[[[109209,27238]],[[109208,27241]],[[109208,27245]],[[109222,27249]],[[109436,27263]]]}}],"UTF8Encoding":true}